ezsnmp/netsnmpbase.py
ezsnmp/_sessionbase.cpython-311-darwin.so
ezsnmp/_exceptionsbase.cpython-311-darwin.so
ezsnmp/_datatypes.cpython-311-darwin.so
ezsnmp/_netsnmpbase.cpython-311-darwin.so
ezsnmp/session.py
ezsnmp/__init__.py
ezsnmp/exceptionsbase.py
ezsnmp/datatypes.py
ezsnmp/netsnmp.py
ezsnmp/exceptions.py
ezsnmp/sessionbase.py
ezsnmp/.dylibs/libnetsnmp.40.dylib
ezsnmp/.dylibs/libcrypto.3.dylib
ezsnmp/.dylibs/libz.1.3.1.dylib
ezsnmp-2.1.0.dist-info/RECORD
ezsnmp-2.1.0.dist-info/WHEEL
ezsnmp-2.1.0.dist-info/top_level.txt
ezsnmp-2.1.0.dist-info/METADATA
ezsnmp-2.1.0.dist-info/licenses/LICENSE
