Metadata-Version: 2.4
Name: ezsnmp
Version: 2.1.0
Summary: A blazingly fast and Pythonic SNMP library based on the official Net-SNMP bindings. We use SWIG to generate the wrapper code for us.
Home-page: https://github.com/carlkidcrypto/ezsnmp
Author: Carlos Santos
Author-email: dose.lucky.sake@cloak.id
Keywords: ezsnmp,net-snmp,easy snmp,easysnmp,snmp,pysnmp,python snmp,snmp library,snmp client,snmp agent,snmp manager,snmp monitoring,network monitoring,network management,mib,network scripting
Platform: Linux 32/64
Platform: MacOS 32/64
Classifier: Development Status :: 4 - Beta
Classifier: Intended Audience :: Developers
Classifier: License :: OSI Approved :: BSD License
Classifier: Operating System :: OS Independent
Classifier: Programming Language :: Python :: 3.9
Classifier: Programming Language :: Python :: 3.10
Classifier: Programming Language :: Python :: 3.11
Classifier: Programming Language :: Python :: 3.12
Classifier: Programming Language :: Python :: 3.13
Classifier: Topic :: System :: Networking
Classifier: Topic :: System :: Networking :: Monitoring
Requires-Python: <3.14,>=3.9
License-File: LICENSE
Dynamic: license-file
